grid_cortex_client/__init__.py
grid_cortex_client/base_model.py
grid_cortex_client/client.py
grid_cortex_client/cortex_client.py
grid_cortex_client/main.py
grid_cortex_client/model_type.py
grid_cortex_client/postprocessing.py
grid_cortex_client/preprocessing.py
grid_cortex_client/utils.py
grid_cortex_client/visualization.py
grid_cortex_client/ws.py
grid_cortex_client/models/__init__.py
grid_cortex_client/models/base_model.py
grid_cortex_client/models/depth.py
grid_cortex_client/models/feature_matcher.py
grid_cortex_client/models/foundation_stereo.py
grid_cortex_client/models/grasp.py
grid_cortex_client/models/graspgen.py
grid_cortex_client/models/gsam2.py
grid_cortex_client/models/moondream.py
grid_cortex_client/models/oneformer.py
grid_cortex_client/models/owlv2.py
grid_cortex_client/models/sam2.py
grid_cortex_client/models/sam2_video.py
grid_cortex_client/models/sam3.py
grid_cortex_client/models/zoedepth.py
grid_cortex_client/tools/__init__.py
grid_cortex_client/tools/generate_enum.py
grid_cortex_client-0.2.43.dist-info/METADATA
grid_cortex_client-0.2.43.dist-info/WHEEL
grid_cortex_client-0.2.43.dist-info/RECORD
