Metadata-Version: 2.4
Name: grid-cortex-client
Version: 0.2.43
Summary: python client for grid cortex
Requires-Python: >=3.8
Requires-Dist: httpx>=0.28.1
Requires-Dist: msgpack-numpy>=0.4.0
Requires-Dist: msgpack>=1.0.0
Requires-Dist: numpy<2
Requires-Dist: pillow>=10.0.0
Requires-Dist: requests>=2.20.0
Requires-Dist: rerun-sdk==0.22.1
Requires-Dist: websocket-client>=1.7
